{
  "lessonId": 11,
  "exercises": [
    {
      "type": "choice",
      "id": "ex-11-01",
      "stem": "为了解某校 $2000$ 名学生的视力情况，随机抽取了 $100$ 名学生进行调查。在这个问题中，样本容量是（  ）",
      "options": [
        { "label": "A", "text": "$100$ 名" },
        { "label": "B", "text": "$100$" },
        { "label": "C", "text": "$2000$" },
        { "label": "D", "text": "$2000$ 名" }
      ],
      "answer": "B",
      "analysis": "样本容量是样本中个体的数目，是一个数，不带单位。所以样本容量是 $100$。",
      "source": "2023年深圳中考"
    },
    {
      "type": "choice",
      "id": "ex-11-02",
      "stem": "甲、乙两组数据的方差分别为 $s_甲^2 = 2.3$，$s_乙^2 = 1.8$，则（  ）",
      "options": [
        { "label": "A", "text": "甲组数据更稳定" },
        { "label": "B", "text": "乙组数据更稳定" },
        { "label": "C", "text": "两组数据一样稳定" },
        { "label": "D", "text": "无法比较" }
      ],
      "answer": "B",
      "analysis": "方差越小，数据越稳定。$s_乙^2 = 1.8 < s_甲^2 = 2.3$，所以乙组数据更稳定。",
      "source": "2022年深圳中考"
    },
    {
      "type": "choice",
      "id": "ex-11-03",
      "stem": "从一批灯泡中随机抽取 $20$ 只进行寿命检测，数据的平均数为 $1000$ 小时，由此可以估计这批灯泡的平均寿命约为（  ）",
      "options": [
        { "label": "A", "text": "$20$ 小时" },
        { "label": "B", "text": "$1000$ 小时" },
        { "label": "C", "text": "$20000$ 小时" },
        { "label": "D", "text": "无法估计" }
      ],
      "answer": "B",
      "analysis": "用样本平均数估计总体平均数，样本平均数为 $1000$ 小时，所以估计这批灯泡的平均寿命约为 $1000$ 小时。",
      "source": ""
    },
    {
      "type": "true_false",
      "id": "ex-11-04",
      "stem": "样本容量越大，用样本估计总体就越准确。",
      "answer": true,
      "analysis": "一般来说，样本容量越大，样本包含的信息越丰富，对总体的估计就越准确。"
    },
    {
      "type": "fill",
      "id": "ex-11-05",
      "segments": ["某班 $40$ 名同学的数学成绩数据，平均数为 $85$ 分，方差为 $16$。由此可估计全年级 $800$ 名同学的数学平均成绩约为 ___1___ 分。"],
      "blanks": [
        { "index": 1, "answer": "$85$" }
      ],
      "analysis": "用样本平均数估计总体平均数，样本平均数为 $85$ 分，所以估计全年级平均成绩约为 $85$ 分。"
    }
  ]
}